slashr/__init__.py
slashr-1.0.0.dist-info/LICENSE
slashr-1.0.0.dist-info/METADATA
slashr-1.0.0.dist-info/WHEEL
slashr-1.0.0.dist-info/top_level.txt
slashr-1.0.0.dist-info/RECORD
