Metadata-Version: 2.1
Name: slashr
Version: 1.0.0
Summary: \r Never lose your cursor again!
Author: Red
Author-email: redtonehair@gmail.com
Keywords: python,terminal
License-File: LICENSE
Requires-Dist: colorama
Requires-Dist: cursor
